<?xml version="1.0" encoding="UTF-8" ?>
<root>
<header>
	<date>2013-12-01</date>
	<tags>
		<tag>Msk</tag>
	</tags>
	<points_per_match>4</points_per_match>
</header>

<matches>
	<match>
		<player1>Щербаков Григорий</player1>
		<player2>Бушмакин Евгений</player2>
		<games>
			<game><score1>0</score1><score2>2</score2></game>
			<game><score1>2</score1><score2>0</score2></game>
		</games>
	</match>
	<match>
		<player1>Гребенщиков Леонид</player1>
		<player2>Борц Ларик</player2>
		<games>
			<game><score1>0</score1><score2>2</score2></game>
			<game><score1>2</score1><score2>0</score2></game>
		</games>
	</match>
	<match>
		<player1>Колмаков Петр</player1>
		<player2>Антонов Евгений</player2>
		<games>
			<game><score1>2</score1><score2>0</score2></game>
			<game><score1>2</score1><score2>0</score2></game>
		</games>
	</match>
	<match>
		<player1>Нащекин Алексей</player1>
		<player2>Рогозин Антон</player2>
		<games>
			<game><score1>0</score1><score2>2</score2></game>
			<game><score1>0</score1><score2>2</score2></game>
		</games>
	</match>
	<match>
		<player1>Данюшевский Петр</player1>
		<player2>Абдулазизов Озод</player2>
		<games>
			<game><score1>2</score1><score2>0</score2></game>
			<game><score1>2</score1><score2>0</score2></game>
		</games>
	</match>
	<match>
		<player1>Ларин Филипп</player1>
		<player2>Леньшин Егор</player2>
		<games>
			<game><score1>0</score1><score2>2</score2></game>
			<game><score1>2</score1><score2>0</score2></game>
		</games>
	</match>
	<match>
		<player1>Данюшевский Петр</player1>
		<player2>Колмаков Петр</player2>
		<games>
			<game><score1>2</score1><score2>0</score2></game>
			<game><score1>2</score1><score2>0</score2></game>
		</games>
	</match>
	<match>
		<player1>Щербаков Григорий</player1>
		<player2>Рогозин Антон</player2>
		<games>
			<game><score1>0</score1><score2>2</score2></game>
			<game><score1>0</score1><score2>2</score2></game>
		</games>
	</match>
	<match>
		<player1>Гребенщиков Леонид</player1>
		<player2>Бушмакин Евгений</player2>
		<games>
			<game><score1>2</score1><score2>0</score2></game>
			<game><score1>2</score1><score2>0</score2></game>
		</games>
	</match>
	<match>
		<player1>Борц Ларик</player1>
		<player2>Ларин Филипп</player2>
		<games>
			<game><score1>2</score1><score2>0</score2></game>
			<game><score1>2</score1><score2>0</score2></game>
		</games>
	</match>
	<match>
		<player1>Нащекин Алексей</player1>
		<player2>Леньшин Егор</player2>
		<games>
			<game><score1>2</score1><score2>0</score2></game>
			<game><score1>2</score1><score2>0</score2></game>
		</games>
	</match>
	<match>
		<player1>Абдулазизов Озод</player1>
		<player2>Антонов Евгений</player2>
		<games>
			<game><score1>2</score1><score2>0</score2></game>
			<game><score1>2</score1><score2>0</score2></game>
		</games>
	</match>
	<match>
		<player1>Данюшевский Петр</player1>
		<player2>Рогозин Антон</player2>
		<games>
			<game><score1>0</score1><score2>2</score2></game>
			<game><score1>2</score1><score2>0</score2></game>
		</games>
	</match>
	<match>
		<player1>Нащекин Алексей</player1>
		<player2>Гребенщиков Леонид</player2>
		<games>
			<game><score1>2</score1><score2>0</score2></game>
			<game><score1>0</score1><score2>1</score2></game>
		</games>
	</match>
	<match>
		<player1>Колмаков Петр</player1>
		<player2>Борц Ларик</player2>
		<games>
			<game><score1>0</score1><score2>2</score2></game>
			<game><score1>0</score1><score2>2</score2></game>
		</games>
	</match>
	<match>
		<player1>Щербаков Григорий</player1>
		<player2>Абдулазизов Озод</player2>
		<games>
			<game><score1>0</score1><score2>2</score2></game>
			<game><score1>0</score1><score2>2</score2></game>
		</games>
	</match>
	<match>
		<player1>Бушмакин Евгений</player1>
		<player2>Ларин Филипп</player2>
		<games>
			<game><score1>0</score1><score2>2</score2></game>
			<game><score1>2</score1><score2>0</score2></game>
		</games>
	</match>
	<match>
		<player1>Антонов Евгений</player1>
		<player2>Леньшин Егор</player2>
		<games>
			<game><score1>0</score1><score2>2</score2></game>
			<game><score1>2</score1><score2>0</score2></game>
		</games>
	</match>
	<match>
		<player1>Данюшевский Петр</player1>
		<player2>Борц Ларик</player2>
		<games>
			<game><score1>0</score1><score2>2</score2></game>
			<game><score1>2</score1><score2>0</score2></game>
		</games>
	</match>
	<match>
		<player1>Абдулазизов Озод</player1>
		<player2>Рогозин Антон</player2>
		<games>
			<game><score1>2</score1><score2>0</score2></game>
			<game><score1>2</score1><score2>0</score2></game>
		</games>
	</match>
	<match>
		<player1>Гребенщиков Леонид</player1>
		<player2>Колмаков Петр</player2>
		<games>
			<game><score1>0</score1><score2>2</score2></game>
			<game><score1>2</score1><score2>0</score2></game>
		</games>
	</match>
	<match>
		<player1>Нащекин Алексей</player1>
		<player2>Ларин Филипп</player2>
		<games>
			<game><score1>2</score1><score2>0</score2></game>
			<game><score1>2</score1><score2>0</score2></game>
		</games>
	</match>
	<match>
		<player1>Бушмакин Евгений</player1>
		<player2>Леньшин Егор</player2>
		<games>
			<game><score1>0</score1><score2>2</score2></game>
			<game><score1>0</score1><score2>2</score2></game>
		</games>
	</match>
	<match>
		<player1>Щербаков Григорий</player1>
		<player2>Антонов Евгений</player2>
		<games>
			<game><score1>0</score1><score2>2</score2></game>
			<game><score1>2</score1><score2>0</score2></game>
		</games>
	</match>
	<match>
		<player1>Борц Ларик</player1>
		<player2>Рогозин Антон</player2>
		<games>
			<game><score1>0</score1><score2>2</score2></game>
			<game><score1>0</score1><score2>2</score2></game>
		</games>
	</match>
	<match>
		<player1>Абдулазизов Озод</player1>
		<player2>Данюшевский Петр</player2>
		<games>
			<game><score1>0</score1><score2>2</score2></game>
			<game><score1>0</score1><score2>2</score2></game>
		</games>
	</match>
	<match>
		<player1>Рогозин Антон</player1>
		<player2>Данюшевский Петр</player2>
		<games>
			<game><score1>2</score1><score2>0</score2></game>
			<game><score1>2</score1><score2>0</score2></game>
		</games>
	</match>
</matches>
</root>
